glogcenter/__init__.py
glogcenter/__version__.py
glogcenter/glc.py
glogcenter-0.17.1.dist-info/LICENSE
glogcenter-0.17.1.dist-info/METADATA
glogcenter-0.17.1.dist-info/WHEEL
glogcenter-0.17.1.dist-info/top_level.txt
glogcenter-0.17.1.dist-info/RECORD
